d7a/__init__.py
d7a/parse_error.py
d7a/alp/__init__.py
d7a/alp/action.py
d7a/alp/command.py
d7a/alp/forward_action.py
d7a/alp/indirect_forward_action.py
d7a/alp/interface.py
d7a/alp/parser.py
d7a/alp/regular_action.py
d7a/alp/status_action.py
d7a/alp/tag_request_action.py
d7a/alp/tag_response_action.py
d7a/alp/operands/__init__.py
d7a/alp/operands/file.py
d7a/alp/operands/file_header.py
d7a/alp/operands/indirect_interface_operand.py
d7a/alp/operands/interface_configuration.py
d7a/alp/operands/interface_status.py
d7a/alp/operands/length.py
d7a/alp/operands/lorawan_interface_configuration_abp.py
d7a/alp/operands/lorawan_interface_configuration_otaa.py
d7a/alp/operands/offset.py
d7a/alp/operands/query.py
d7a/alp/operands/tag_id.py
d7a/alp/operations/__init__.py
d7a/alp/operations/break_query.py
d7a/alp/operations/file_management.py
d7a/alp/operations/forward.py
d7a/alp/operations/indirect_forward.py
d7a/alp/operations/nop.py
d7a/alp/operations/operation.py
d7a/alp/operations/requests.py
d7a/alp/operations/responses.py
d7a/alp/operations/status.py
d7a/alp/operations/tag_request.py
d7a/alp/operations/tag_response.py
d7a/alp/operations/write_operations.py
d7a/d7anp/__init__.py
d7a/d7anp/addressee.py
d7a/d7anp/control.py
d7a/d7anp/frame.py
d7a/d7atp/__init__.py
d7a/d7atp/control.py
d7a/d7atp/frame.py
d7a/dll/__init__.py
d7a/dll/access_profile.py
d7a/dll/background_frame.py
d7a/dll/background_frame_control.py
d7a/dll/foreground_frame.py
d7a/dll/foreground_frame_control.py
d7a/dll/parser.py
d7a/dll/sub_profile.py
d7a/fs/__init__.py
d7a/fs/file_header.py
d7a/fs/file_permissions.py
d7a/fs/file_properties.py
d7a/phy/__init__.py
d7a/phy/channel_header.py
d7a/phy/channel_id.py
d7a/phy/channel_status_identifier.py
d7a/phy/subband.py
d7a/serial_modem_interface/__init__.py
d7a/serial_modem_interface/parser.py
d7a/serial_modem_interface/examples/__init__.py
d7a/serial_modem_interface/examples/generate_messages.py
d7a/sp/__init__.py
d7a/sp/autoscaling_ctrl.py
d7a/sp/configuration.py
d7a-0.1.1.dist-info/METADATA
d7a-0.1.1.dist-info/WHEEL
d7a-0.1.1.dist-info/entry_points.txt
d7a-0.1.1.dist-info/licenses/LICENSE
d7a-0.1.1.dist-info/RECORD
