Metadata-Version: 2.3
Name: d7a
Version: 0.1.1
Summary: Python Dash7 ALP library
Author-email: Glenn Ergeerts <glenn.ergeerts@aloxy.io>, Liam Oorts <liam.oorts@aloxy.io>, Kwinten Schram <kwinten.schram@aloxy.io>, Dirk Van Haerenborgh <dirk.vanhaerenborgh@aloxy.io>, Bart Jonkers <bart.jonkers@aloxy.io>, Jolanta Tadla <jolanta.tadla@aloxy.io>
License: Apache-2.0
License-File: LICENSE
Requires-Python: <4.0,>=3.8
Requires-Dist: bitstring<4.0.0,>=3.1.7
Requires-Dist: cerberus<2.0.0,>=1.3.5
Requires-Dist: crcmod<2.0,>=1.7
Requires-Dist: jsonpickle<4.0,>=3.0
Provides-Extra: examples
Requires-Dist: paho-mqtt<2.0.0,>=1.6.1; extra == 'examples'
Requires-Dist: pyserial<4.0.0,>=3.5.0; extra == 'examples'
Requires-Dist: traceback2<2.0.0,>=1.4.0; extra == 'examples'
